pystructure/__init__.py
pystructure/pystructure.py
pystructure-1.1.0.dist-info/DESCRIPTION.rst
pystructure-1.1.0.dist-info/METADATA
pystructure-1.1.0.dist-info/RECORD
pystructure-1.1.0.dist-info/WHEEL
pystructure-1.1.0.dist-info/entry_points.txt
pystructure-1.1.0.dist-info/metadata.json
pystructure-1.1.0.dist-info/top_level.txt
pystructure-1.1.0.dist-info/zip-safe
