Metadata-Version: 2.0
Name: pystructure
Version: 1.1.0
Summary: a simple tool to show code structure about python source code
Home-page: https://github.com/hanks/pystructure
Author: hanks
Author-email: zhouhan315@gmail.com
License: MIT License
Requires-Dist: docopt (>=0.6.2)
